openvpnclient.py
python_openvpn_client-0.0.1.dist-info/LICENSE
python_openvpn_client-0.0.1.dist-info/METADATA
python_openvpn_client-0.0.1.dist-info/WHEEL
python_openvpn_client-0.0.1.dist-info/top_level.txt
python_openvpn_client-0.0.1.dist-info/RECORD
