Metadata-Version: 2.1
Name: python-openvpn-client
Version: 0.0.1
Summary: An API for managing an OpenVPN connection
Author-email: Ludvig Larsson <lular@kth.se>, Nikolaos Kakouros <nkak@kth.se>, Benjamin Kelley <bekelley@kth.se>
Project-URL: Homepage, https://github.com/KTH-SSAS/python-openvpn-client
Project-URL: Issues, https://github.com/KTH-SSAS/python-openvpn-client/issues
Classifier: Programming Language :: Python :: 3
Classifier: Development Status :: 4 - Beta
Classifier: License :: OSI Approved :: MIT License
Classifier: Operating System :: POSIX :: Linux
Classifier: Operating System :: MacOS
Requires-Python: >=3.9
License-File: LICENSE
Requires-Dist: psutil
Requires-Dist: docopt
Requires-Dist: typing-extensions
